chaos_box/__init__.py
chaos_box/cmd/apt_lists.py
chaos_box/cmd/archive_dirs.py
chaos_box/cmd/archive_mobi.py
chaos_box/cmd/date_rename.py
chaos_box/cmd/deb_extract.py
chaos_box/cmd/enc_recover.py
chaos_box/cmd/halfwidth.py
chaos_box/cmd/iconv8.py
chaos_box/cmd/ifstats.py
chaos_box/cmd/ipmerge.py
chaos_box/cmd/pascal.py
chaos_box/cmd/prime.py
chaos_box/cmd/qbt_dump.py
chaos_box/cmd/qbt_migrate.py
chaos_box/cmd/qbt_tracker.py
chaos_box/cmd/qrcode_merge.py
chaos_box/cmd/qrcode_split.py
chaos_box/cmd/rotate_images.py
chaos_box/cmd/shasum_list.py
chaos_box/cmd/sort_keys.py
chaos_box/cmd/urlencode.py
chaos_box-0.5.0.dist-info/METADATA
chaos_box-0.5.0.dist-info/WHEEL
chaos_box-0.5.0.dist-info/entry_points.txt
chaos_box-0.5.0.dist-info/licenses/LICENSE
chaos_box-0.5.0.dist-info/RECORD
