Metadata-Version: 2.4
Name: chaos-box
Version: 0.5.0
Summary: Collection of handy utils written in Python 3
Project-URL: Homepage, https://github.com/ak1ra-lab/chaos-box
Project-URL: Changelog, https://github.com/ak1ra-lab/chaos-box/blob/master/CHANGELOG.md
Author-email: ak1ra <git@ak1ra.xyz>
License-Expression: MIT
License-File: LICENSE
Keywords: archive,bittorrent,checksum,cli,commandline,compression,debian,file-renaming,image-rotation,ip-address,json,network,qbittorrent,qrcode,system-tools,text-processing,url-encoding,utility
Classifier: Development Status :: 4 - Beta
Classifier: Environment :: Console
Classifier: Intended Audience :: System Administrators
Classifier: Operating System :: OS Independent
Classifier: Programming Language :: Python :: 3
Classifier: Programming Language :: Python :: 3 :: Only
Classifier: Programming Language :: Python :: 3.11
Classifier: Programming Language :: Python :: 3.12
Classifier: Programming Language :: Python :: 3.13
Classifier: Topic :: Multimedia :: Graphics
Classifier: Topic :: System :: Archiving
Classifier: Topic :: System :: Filesystems
Classifier: Topic :: System :: Networking
Classifier: Topic :: Text Processing
Classifier: Topic :: Utilities
Requires-Python: >=3.11
Requires-Dist: argcomplete>=3.6.2
Requires-Dist: chaos-utils>=0.1.0
Requires-Dist: fastbencode>=0.3.2
Requires-Dist: httpx>=0.28.1
Requires-Dist: mobi>=0.3.3
Requires-Dist: netaddr>=1.3.0
Requires-Dist: numpy>=2.3.0
Requires-Dist: opencv-python-headless>=4.11.0.86
Requires-Dist: pillow>=11.2.1
Requires-Dist: psutil>=7.0.0
Requires-Dist: py7zr>=1.0.0
Requires-Dist: pypng>=0.20220715.0
Requires-Dist: python-debian>=1.0.1
Requires-Dist: pyzbar>=0.1.9
Requires-Dist: qbittorrent-api>=2025.7.0
Requires-Dist: qrcode>=8.2
